videoanalytics/__init__.py
videoanalytics/utils.py
videoanalytics/pipeline/__init__.py
videoanalytics/pipeline/sinks/__init__.py
videoanalytics/pipeline/sinks/background.py
videoanalytics/pipeline/sinks/influxdb.py
videoanalytics/pipeline/sinks/obj_detector.py
videoanalytics/pipeline/sinks/resizer.py
videoanalytics/pipeline/sinks/roi.py
videoanalytics/pipeline/sinks/yolo4_detector.py
videoanalytics/pipeline/sinks/zmqpub.py
videoanalytics/pipeline/sinks/trackers/__init__.py
videoanalytics/pipeline/sinks/trackers/sort.py
videoanalytics/pipeline/sources/__init__.py
videoanalytics-0.0.2.dist-info/LICENSE
videoanalytics-0.0.2.dist-info/METADATA
videoanalytics-0.0.2.dist-info/WHEEL
videoanalytics-0.0.2.dist-info/top_level.txt
videoanalytics-0.0.2.dist-info/RECORD
