Metadata-Version: 2.1
Name: videoanalytics
Version: 0.0.2
Summary: Library for prototyping video analytic applicatios.
Home-page: https://github.com/nhorro/videoanalytics
Author: Nicolás Eduardo Horro
Author-email: nhorro@gmail.com
License: UNKNOWN
Project-URL: Bug Tracker, https://github.com/nhorro/videoanalytics/issues
Platform: UNKNOWN
Classifier: Programming Language :: Python :: 3
Classifier: License :: OSI Approved :: MIT License
Classifier: Operating System :: OS Independent
Requires-Python: >=3.6
License-File: LICENSE
